queue_system/__init__.py
queue_system/queue_receiver.py
queue_system/queue_sender.py
queue_system-0.0.1.dist-info/METADATA
queue_system-0.0.1.dist-info/RECORD
queue_system-0.0.1.dist-info/WHEEL
queue_system-0.0.1.dist-info/top_level.txt
