Metadata-Version: 2.1
Name: queue-system
Version: 0.0.1
Summary: Publisher and consumer written for rabbitMQ
Home-page: UNKNOWN
Author: Matej Jularic
Author-email: matej@morpheuszone.com
License: UNKNOWN
Platform: UNKNOWN
Classifier: Programming Language :: Python :: 3
Classifier: License :: OSI Approved :: MIT License
Classifier: Operating System :: OS Independent
Requires-Dist: pika
